[
    {
        "type": "link",
        "sizes": [
            "728x90",
            "468x60",
            "300x600",
            "300x250",
            "160x600",
            "120x600"
        ],
        "tcs": [
            "134342",
            "134351",
            "134360",
            "134369",
            "134378",
            "134387"
        ],
        "name": "civitatis-it_adg_SEASONALITY_dis_prs-1_IT_IT_AWARENESS_PROS_REACH_2024_VERANO_HOME_SICILIA",
        "landing": "https://www.civitatis.com/it/",
        "aws_path_1": "CIVITATIS/2024/06/reach/sicilia/",
        "aws_path_2": ".gif",
        "url": "https://www.civitatis.com/it/?aid=108&cmp=it_IT&cmpint=adg_it_SICILIA_728x90&utm_source=adg&utm_medium=dis-prs-1&utm_campaign=awareness&utm_term=it_IT_Awareness_PROS_Reach_2024_Verano_Home_Sicilia&utm_content=SICILIA",
        "viewability": "//bucket.cdnwebcloud.com/n_one_vway_civitatis-es_np_"
    },
    {
        "type": "link",
        "sizes": [
            "728x90",
            "468x60",
            "300x600",
            "300x250",
            "160x600",
            "120x600"
        ],
        "tcs": [
            "134343",
            "134352",
            "134361",
            "134370",
            "134379",
            "134388"
        ],
        "name": "civitatis-it_adg_SEASONALITY_dis_prs-1_IT_IT_AWARENESS_PROS_REACH_2024_VERANO_HOME_ROMA",
        "landing": "https://www.civitatis.com/it/",
        "aws_path_1": "CIVITATIS/2024/06/reach/roma/",
        "aws_path_2": ".gif",
        "url": "https://www.civitatis.com/it/?aid=108&cmp=it_IT&cmpint=adg_it_ROMA_728x90&utm_source=adg&utm_medium=dis-prs-1&utm_campaign=awareness&utm_term=it_IT_Awareness_PROS_Reach_2024_Verano_Home_Roma&utm_content=ROMA",
        "viewability": "//bucket.cdnwebcloud.com/n_one_vway_civitatis-es_np_"
    },
    {
        "type": "link",
        "sizes": [
            "728x90",
            "468x60",
            "300x600",
            "300x250",
            "160x600",
            "120x600"
        ],
        "tcs": [
            "134344",
            "134353",
            "134362",
            "134371",
            "134380",
            "134389"
        ],
        "name": "civitatis-it_adg_SEASONALITY_dis_prs-1_IT_IT_AWARENESS_PROS_REACH_2024_VERANO_HOME_NY",
        "landing": "https://www.civitatis.com/it/",
        "aws_path_1": "CIVITATIS/2024/06/reach/ny/",
        "aws_path_2": ".gif",
        "url": "https://www.civitatis.com/it/?aid=108&cmp=it_IT&cmpint=adg_it_NYC_728x90&utm_source=adg&utm_medium=dis-prs-1&utm_campaign=awareness&utm_term=it_IT_Awareness_PROS_Reach_2024_Verano_Home_NY&utm_content=NYC",
        "viewability": "//bucket.cdnwebcloud.com/n_one_vway_civitatis-es_np_"
    },
    {
        "type": "link",
        "sizes": [
            "728x90",
            "468x60",
            "300x600",
            "300x250",
            "160x600",
            "120x600"
        ],
        "tcs": [
            "134345",
            "134354",
            "134363",
            "134372",
            "134381",
            "134390"
        ],
        "name": "civitatis-it_adg_SEASONALITY_dis_prs-1_IT_IT_AWARENESS_PROS_REACH_2024_VERANO_HOME_MEDELLIIN",
        "landing": "https://www.civitatis.com/it/",
        "aws_path_1": "CIVITATIS/2024/06/reach/",
        "aws_path_2": ".gif",
        "url": "https://www.civitatis.com/it/?aid=108&cmp=it_IT&cmpint=adg_it_MEDELLIN_728x90&utm_source=adg&utm_medium=dis-prs-1&utm_campaign=awareness&utm_term=it_IT_Awareness_PROS_Reach_2024_Verano_Home_Medelliin&utm_content=MEDELLIN",
        "viewability": "//bucket.cdnwebcloud.com/n_one_vway_civitatis-es_np_"
    },
    {
        "type": "link",
        "sizes": [
            "728x90",
            "468x60",
            "300x600",
            "300x250",
            "160x600",
            "120x600"
        ],
        "tcs": [
            "134346",
            "134355",
            "134364",
            "134373",
            "134382",
            "134391"
        ],
        "name": "civitatis-it_adg_SEASONALITY_dis_prs-1_IT_IT_AWARENESS_PROS_REACH_2024_VERANO_HOME_LISBOA",
        "landing": "https://www.civitatis.com/it/",
        "aws_path_1": "CIVITATIS/2024/06/reach/lisboa/",
        "aws_path_2": ".gif",
        "url": "https://www.civitatis.com/it/?aid=108&cmp=it_IT&cmpint=adg_it_LISBOA_728x90&utm_source=adg&utm_medium=dis-prs-1&utm_campaign=awareness&utm_term=it_IT_Awareness_PROS_Reach_2024_Verano_Home_Lisboa&utm_content=LISBOA",
        "viewability": "//bucket.cdnwebcloud.com/n_one_vway_civitatis-es_np_"
    },
    {
        "type": "link",
        "sizes": [
            "728x90",
            "468x60",
            "300x600",
            "300x250",
            "160x600",
            "120x600"
        ],
        "tcs": [
            "134347",
            "134356",
            "134365",
            "134374",
            "134383",
            "134392"
        ],
        "name": "civitatis-it_adg_SEASONALITY_dis_prs-1_IT_IT_AWARENESS_PROS_REACH_2024_VERANO_HOME_FORMENTERA",
        "landing": "https://www.civitatis.com/it/",
        "aws_path_1": "CIVITATIS/2024/06/reach/formentera/",
        "aws_path_2": ".gif",
        "url": "https://www.civitatis.com/it/?aid=108&cmp=it_IT&cmpint=adg_it_FORMENTERA_728x90&utm_source=adg&utm_medium=dis-prs-1&utm_campaign=awareness&utm_term=it_IT_Awareness_PROS_Reach_2024_Verano_Home_Formentera&utm_content=FORMENTERA",
        "viewability": "//bucket.cdnwebcloud.com/n_one_vway_civitatis-es_np_"
    },
    {
        "type": "link",
        "sizes": [
            "728x90",
            "468x60",
            "300x600",
            "300x250",
            "160x600",
            "120x600"
        ],
        "tcs": [
            "134348",
            "134357",
            "134366",
            "134375",
            "134384",
            "134393"
        ],
        "name": "civitatis-it_adg_SEASONALITY_dis_prs-1_IT_IT_AWARENESS_PROS_REACH_2024_VERANO_HOME_FLORENCIA",
        "landing": "https://www.civitatis.com/it/",
        "aws_path_1": "CIVITATIS/2024/06/reach/florencia/",
        "aws_path_2": ".gif",
        "url": "https://www.civitatis.com/it/?aid=108&cmp=it_IT&cmpint=adg_it_FLORENCIA_728x90&utm_source=adg&utm_medium=dis-prs-1&utm_campaign=awareness&utm_term=it_IT_Awareness_PROS_Reach_2024_Verano_Home_Florencia&utm_content=FLORENCIA",
        "viewability": "//bucket.cdnwebcloud.com/n_one_vway_civitatis-es_np_"
    },
    {
        "type": "link",
        "sizes": [
            "728x90",
            "468x60",
            "300x600",
            "300x250",
            "160x600",
            "120x600"
        ],
        "tcs": [
            "134349",
            "134358",
            "134367",
            "134376",
            "134385",
            "134394"
        ],
        "name": "civitatis-it_adg_SEASONALITY_dis_prs-1_IT_IT_AWARENESS_PROS_REACH_2024_VERANO_HOME_CRACOVIA",
        "landing": "https://www.civitatis.com/it/",
        "aws_path_1": "CIVITATIS/2024/06/reach/cracovia/",
        "aws_path_2": ".gif",
        "url": "https://www.civitatis.com/it/?aid=108&cmp=it_IT&cmpint=adg_it_CRACOVIA_728x90&utm_source=adg&utm_medium=dis-prs-1&utm_campaign=awareness&utm_term=it_IT_Awareness_PROS_Reach_2024_Verano_Home_Cracovia&utm_content=CRACOVIA",
        "viewability": "//bucket.cdnwebcloud.com/n_one_vway_civitatis-es_np_"
    },
    {
        "type": "link",
        "sizes": [
            "728x90",
            "468x60",
            "300x600",
            "300x250",
            "160x600",
            "120x600"
        ],
        "tcs": [
            "134350",
            "134359",
            "134368",
            "134377",
            "134386",
            "134395"
        ],
        "name": "civitatis-it_adg_SEASONALITY_dis_prs-1_IT_IT_AWARENESS_PROS_REACH_2024_VERANO_HOME_CAIRO",
        "landing": "https://www.civitatis.com/it/",
        "aws_path_1": "CIVITATIS/2024/06/reach/cairo/",
        "aws_path_2": ".gif",
        "url": "https://www.civitatis.com/it/?aid=108&cmp=it_IT&cmpint=adg_it_CAIRO_728x90&utm_source=adg&utm_medium=dis-prs-1&utm_campaign=awareness&utm_term=it_IT_Awareness_PROS_Reach_2024_Verano_Home_Cairo&utm_content=CAIRO",
        "viewability": "//bucket.cdnwebcloud.com/n_one_vway_civitatis-es_np_"
    }
]