[
    {
        "type": "link",
        "sizes": [
            "160x600"
        ],
        "tcs": [],
        "name": "volaris-mx_adg_ABRIL24_dis_prs-1_VEGAS-JULIO",
        "landing": "https://a2.adform.net/C/?bn=74764285",
        "aws_path_1": "VOLARIS/2024/07/vegas/",
        "aws_path_2": ".jpg",
        "url": "https://a2.adform.net/C/?bn=74764285",
        "impression_tag": "<img src='https://a2.adform.net/adfserve/?bn=74764285;1x1inv=1;srctype=3;ord=[timestamp]' border='0' width='1' height='1'/>"
    },
    {
        "type": "link",
        "sizes": [
            "300x250"
        ],
        "tcs": [],
        "name": "volaris-mx_adg_ABRIL24_dis_prs-1_VEGAS-JULIO",
        "landing": "https://a2.adform.net/C/?bn=74764299",
        "aws_path_1": "VOLARIS/2024/07/vegas/",
        "aws_path_2": ".jpg",
        "url": "https://a2.adform.net/C/?bn=74764299",
        "impression_tag": "<img src='https://a2.adform.net/adfserve/?bn=74764299;1x1inv=1;srctype=3;ord=[timestamp]' border='0' width='1' height='1'/>"
    },
    {
        "type": "link",
        "sizes": [
            "300x600"
        ],
        "tcs": [],
        "name": "volaris-mx_adg_ABRIL24_dis_prs-1_VEGAS-JULIO",
        "landing": "https://a2.adform.net/C/?bn=74764276",
        "aws_path_1": "VOLARIS/2024/07/vegas/",
        "aws_path_2": ".jpg",
        "url": "https://a2.adform.net/C/?bn=74764276",
        "impression_tag": "<img src='https://a2.adform.net/adfserve/?bn=74764276;1x1inv=1;srctype=3;ord=[timestamp]' border='0' width='1' height='1'/>"
    },
    {
        "type": "link",
        "sizes": [
            "468x60"
        ],
        "tcs": [],
        "name": "volaris-mx_adg_ABRIL24_dis_prs-1_VEGAS-JULIO",
        "landing": "https://a2.adform.net/C/?bn=74764293",
        "aws_path_1": "VOLARIS/2024/07/vegas/",
        "aws_path_2": ".jpg",
        "url": "https://a2.adform.net/C/?bn=74764293",
        "impression_tag": "<img src='https://a2.adform.net/adfserve/?bn=74764293;1x1inv=1;srctype=3;ord=[timestamp]' border='0' width='1' height='1'/>"
    },
    {
        "type": "link",
        "sizes": [
            "728x90"
        ],
        "tcs": [],
        "name": "volaris-mx_adg_ABRIL24_dis_prs-1_VEGAS-JULIO",
        "landing": "https://a2.adform.net/C/?bn=74764280",
        "aws_path_1": "VOLARIS/2024/07/vegas/",
        "aws_path_2": ".jpg",
        "url": "https://a2.adform.net/C/?bn=74764280",
        "impression_tag": "<img src='https://a2.adform.net/adfserve/?bn=74764280;1x1inv=1;srctype=3;ord=[timestamp]' border='0' width='1' height='1'/>"
    },
    {
        "type": "link",
        "sizes": [
            "160x600"
        ],
        "tcs": [],
        "name": "volaris-mx_adg_ABRIL24_dis_prs-1_AVA-JULIO",
        "landing": "https://a2.adform.net/C/?bn=74764287",
        "aws_path_1": "VOLARIS/2024/07/ava/",
        "aws_path_2": ".jpg",
        "url": "https://a2.adform.net/C/?bn=74764287",
        "impression_tag": "<img src='https://a2.adform.net/adfserve/?bn=74764287;1x1inv=1;srctype=3;ord=[timestamp]' border='0' width='1' height='1'/>"
    },
    {
        "type": "link",
        "sizes": [
            "300x250"
        ],
        "tcs": [],
        "name": "volaris-mx_adg_ABRIL24_dis_prs-1_AVA-JULIO",
        "landing": "https://a2.adform.net/C/?bn=74764262",
        "aws_path_1": "VOLARIS/2024/07/ava/",
        "aws_path_2": ".jpg",
        "url": "https://a2.adform.net/C/?bn=74764262",
        "impression_tag": "<img src='https://a2.adform.net/adfserve/?bn=74764262;1x1inv=1;srctype=3;ord=[timestamp]' border='0' width='1' height='1'/>"
    },
    {
        "type": "link",
        "sizes": [
            "300x600"
        ],
        "tcs": [],
        "name": "volaris-mx_adg_ABRIL24_dis_prs-1_AVA-JULIO",
        "landing": "https://a2.adform.net/C/?bn=74764289",
        "aws_path_1": "VOLARIS/2024/07/ava/",
        "aws_path_2": ".jpg",
        "url": "https://a2.adform.net/C/?bn=74764289",
        "impression_tag": "<img src='https://a2.adform.net/adfserve/?bn=74764289;1x1inv=1;srctype=3;ord=[timestamp]' border='0' width='1' height='1'/>"
    },
    {
        "type": "link",
        "sizes": [
            "468x60"
        ],
        "tcs": [],
        "name": "volaris-mx_adg_ABRIL24_dis_prs-1_AVA-JULIO",
        "landing": "https://a2.adform.net/C/?bn=74764279",
        "aws_path_1": "VOLARIS/2024/07/ava/",
        "aws_path_2": ".jpg",
        "url": "https://a2.adform.net/C/?bn=74764279",
        "impression_tag": "<img src='https://a2.adform.net/adfserve/?bn=74764279;1x1inv=1;srctype=3;ord=[timestamp]' border='0' width='1' height='1'/>"
    },
    {
        "type": "link",
        "sizes": [
            "728x90"
        ],
        "tcs": [],
        "name": "volaris-mx_adg_ABRIL24_dis_prs-1_AVA-JULIO",
        "landing": "https://a2.adform.net/C/?bn=74764296",
        "aws_path_1": "VOLARIS/2024/07/ava/",
        "aws_path_2": ".jpg",
        "url": "https://a2.adform.net/C/?bn=74764296",
        "impression_tag": "<img src='https://a2.adform.net/adfserve/?bn=74764296;1x1inv=1;srctype=3;ord=[timestamp]' border='0' width='1' height='1'/>"
    },
    {
        "type": "link",
        "sizes": [
            "160x600"
        ],
        "tcs": [],
        "name": "volaris-mx_adg_ABRIL24_dis_prs-1_PLAYAS-JULIO",
        "landing": "https://a2.adform.net/C/?bn=74764297",
        "aws_path_1": "VOLARIS/2024/07/playas/",
        "aws_path_2": ".jpg",
        "url": "https://a2.adform.net/C/?bn=74764297",
        "impression_tag": "<img src='https://a2.adform.net/adfserve/?bn=74764297;1x1inv=1;srctype=3;ord=[timestamp]' border='0' width='1' height='1'/>"
    },
    {
        "type": "link",
        "sizes": [
            "300x250"
        ],
        "tcs": [],
        "name": "volaris-mx_adg_ABRIL24_dis_prs-1_PLAYAS-JULIO",
        "landing": "https://a2.adform.net/C/?bn=74764282",
        "aws_path_1": "VOLARIS/2024/07/playas/",
        "aws_path_2": ".jpg",
        "url": "https://a2.adform.net/C/?bn=74764282",
        "impression_tag": "<img src='https://a2.adform.net/adfserve/?bn=74764282;1x1inv=1;srctype=3;ord=[timestamp]' border='0' width='1' height='1'/>"
    },
    {
        "type": "link",
        "sizes": [
            "300x600"
        ],
        "tcs": [],
        "name": "volaris-mx_adg_ABRIL24_dis_prs-1_PLAYAS-JULIO",
        "landing": "https://a2.adform.net/C/?bn=74764270",
        "aws_path_1": "VOLARIS/2024/07/playas/",
        "aws_path_2": ".jpg",
        "url": "https://a2.adform.net/C/?bn=74764270",
        "impression_tag": "<img src='https://a2.adform.net/adfserve/?bn=74764270;1x1inv=1;srctype=3;ord=[timestamp]' border='0' width='1' height='1'/>"
    },
    {
        "type": "link",
        "sizes": [
            "468x60"
        ],
        "tcs": [],
        "name": "volaris-mx_adg_ABRIL24_dis_prs-1_PLAYAS-JULIO",
        "landing": "https://a2.adform.net/C/?bn=74764283",
        "aws_path_1": "VOLARIS/2024/07/playas/",
        "aws_path_2": ".jpg",
        "url": "https://a2.adform.net/C/?bn=74764283",
        "impression_tag": "<img src='https://a2.adform.net/adfserve/?bn=74764283;1x1inv=1;srctype=3;ord=[timestamp]' border='0' width='1' height='1'/>"
    },
    {
        "type": "link",
        "sizes": [
            "728x90"
        ],
        "tcs": [],
        "name": "volaris-mx_adg_ABRIL24_dis_prs-1_PLAYAS-JULIO",
        "landing": "https://a2.adform.net/C/?bn=74764292",
        "aws_path_1": "VOLARIS/2024/07/playas/",
        "aws_path_2": ".jpg",
        "url": "https://a2.adform.net/C/?bn=74764292",
        "impression_tag": "<img src='https://a2.adform.net/adfserve/?bn=74764292;1x1inv=1;srctype=3;ord=[timestamp]' border='0' width='1' height='1'/>"
    },
    {
        "type": "link",
        "sizes": [
            "160x600"
        ],
        "tcs": [],
        "name": "volaris-mx_adg_ABRIL24_dis_prs-1_OUTLET-JULIO",
        "landing": "https://a2.adform.net/C/?bn=74764275",
        "aws_path_1": "VOLARIS/2024/07/outlet/",
        "aws_path_2": ".jpg",
        "url": "https://a2.adform.net/C/?bn=74764275",
        "impression_tag": "<img src='https://a2.adform.net/adfserve/?bn=74764275;1x1inv=1;srctype=3;ord=[timestamp]' border='0' width='1' height='1'/>"
    },
    {
        "type": "link",
        "sizes": [
            "300x250"
        ],
        "tcs": [],
        "name": "volaris-mx_adg_ABRIL24_dis_prs-1_OUTLET-JULIO",
        "landing": "https://a2.adform.net/C/?bn=74764268",
        "aws_path_1": "VOLARIS/2024/07/outlet/",
        "aws_path_2": ".jpg",
        "url": "https://a2.adform.net/C/?bn=74764268",
        "impression_tag": "<img src='https://a2.adform.net/adfserve/?bn=74764268;1x1inv=1;srctype=3;ord=[timestamp]' border='0' width='1' height='1'/>"
    },
    {
        "type": "link",
        "sizes": [
            "300x600"
        ],
        "tcs": [],
        "name": "volaris-mx_adg_ABRIL24_dis_prs-1_OUTLET-JULIO",
        "landing": "https://a2.adform.net/C/?bn=74764274",
        "aws_path_1": "VOLARIS/2024/07/outlet/",
        "aws_path_2": ".jpg",
        "url": "https://a2.adform.net/C/?bn=74764274",
        "impression_tag": "<img src='https://a2.adform.net/adfserve/?bn=74764274;1x1inv=1;srctype=3;ord=[timestamp]' border='0' width='1' height='1'/>"
    },
    {
        "type": "link",
        "sizes": [
            "468x60"
        ],
        "tcs": [],
        "name": "volaris-mx_adg_ABRIL24_dis_prs-1_OUTLET-JULIO",
        "landing": "https://a2.adform.net/C/?bn=74764281",
        "aws_path_1": "VOLARIS/2024/07/outlet/",
        "aws_path_2": ".jpg",
        "url": "https://a2.adform.net/C/?bn=74764281",
        "impression_tag": "<img src='https://a2.adform.net/adfserve/?bn=74764281;1x1inv=1;srctype=3;ord=[timestamp]' border='0' width='1' height='1'/>"
    },
    {
        "type": "link",
        "sizes": [
            "728x90"
        ],
        "tcs": [],
        "name": "volaris-mx_adg_ABRIL24_dis_prs-1_OUTLET-JULIO",
        "landing": "https://a2.adform.net/C/?bn=74764302",
        "aws_path_1": "VOLARIS/2024/07/outlet/",
        "aws_path_2": ".jpg",
        "url": "https://a2.adform.net/C/?bn=74764302",
        "impression_tag": "<img src='https://a2.adform.net/adfserve/?bn=74764302;1x1inv=1;srctype=3;ord=[timestamp]' border='0' width='1' height='1'/>"
    },
    {
        "type": "link",
        "sizes": [
            "160x600"
        ],
        "tcs": [],
        "name": "volaris-mx_adg_ABRIL24_dis_prs-1_COZUMEL-JULIO",
        "landing": "https://a2.adform.net/C/?bn=74764278",
        "aws_path_1": "VOLARIS/2024/07/cozumel/",
        "aws_path_2": ".jpg",
        "url": "https://a2.adform.net/C/?bn=74764278",
        "impression_tag": "<img src='https://a2.adform.net/adfserve/?bn=74764278;1x1inv=1;srctype=3;ord=[timestamp]' border='0' width='1' height='1'/>"
    },
    {
        "type": "link",
        "sizes": [
            "300x250"
        ],
        "tcs": [],
        "name": "volaris-mx_adg_ABRIL24_dis_prs-1_COZUMEL-JULIO",
        "landing": "https://a2.adform.net/C/?bn=74764288",
        "aws_path_1": "VOLARIS/2024/07/cozumel/",
        "aws_path_2": ".jpg",
        "url": "https://a2.adform.net/C/?bn=74764288",
        "impression_tag": "<img src='https://a2.adform.net/adfserve/?bn=74764288;1x1inv=1;srctype=3;ord=[timestamp]' border='0' width='1' height='1'/>"
    },
    {
        "type": "link",
        "sizes": [
            "300x600"
        ],
        "tcs": [],
        "name": "volaris-mx_adg_ABRIL24_dis_prs-1_COZUMEL-JULIO",
        "landing": "https://a2.adform.net/C/?bn=74764300",
        "aws_path_1": "VOLARIS/2024/07/cozumel/",
        "aws_path_2": ".jpg",
        "url": "https://a2.adform.net/C/?bn=74764300",
        "impression_tag": "<img src='https://a2.adform.net/adfserve/?bn=74764300;1x1inv=1;srctype=3;ord=[timestamp]' border='0' width='1' height='1'/>"
    },
    {
        "type": "link",
        "sizes": [
            "468x60"
        ],
        "tcs": [],
        "name": "volaris-mx_adg_ABRIL24_dis_prs-1_COZUMEL-JULIO",
        "landing": "https://a2.adform.net/C/?bn=74764271",
        "aws_path_1": "VOLARIS/2024/07/cozumel/",
        "aws_path_2": ".jpg",
        "url": "https://a2.adform.net/C/?bn=74764271",
        "impression_tag": "<img src='https://a2.adform.net/adfserve/?bn=74764271;1x1inv=1;srctype=3;ord=[timestamp]' border='0' width='1' height='1'/>"
    },
    {
        "type": "link",
        "sizes": [
            "728x90"
        ],
        "tcs": [],
        "name": "volaris-mx_adg_ABRIL24_dis_prs-1_COZUMEL-JULIO",
        "landing": "https://a2.adform.net/C/?bn=74764265",
        "aws_path_1": "VOLARIS/2024/07/cozumel/",
        "aws_path_2": ".jpg",
        "url": "https://a2.adform.net/C/?bn=74764265",
        "impression_tag": "<img src='https://a2.adform.net/adfserve/?bn=74764265;1x1inv=1;srctype=3;ord=[timestamp]' border='0' width='1' height='1'/>"
    },
    {
        "type": "link",
        "sizes": [
            "160x600"
        ],
        "tcs": [],
        "name": "volaris-mx_adg_ABRIL24_dis_prs-1_HILTON-JULIO",
        "landing": "https://a2.adform.net/C/?bn=74764294",
        "aws_path_1": "VOLARIS/2024/07/hilton/",
        "aws_path_2": ".jpg",
        "url": "https://a2.adform.net/C/?bn=74764294",
        "impression_tag": "<img src='https://a2.adform.net/adfserve/?bn=74764294;1x1inv=1;srctype=3;ord=[timestamp]' border='0' width='1' height='1'/>"
    },
    {
        "type": "link",
        "sizes": [
            "300x250"
        ],
        "tcs": [],
        "name": "volaris-mx_adg_ABRIL24_dis_prs-1_HILTON-JULIO",
        "landing": "https://a2.adform.net/C/?bn=74764267",
        "aws_path_1": "VOLARIS/2024/07/hilton/",
        "aws_path_2": ".jpg",
        "url": "https://a2.adform.net/C/?bn=74764267",
        "impression_tag": "<img src='https://a2.adform.net/adfserve/?bn=74764267;1x1inv=1;srctype=3;ord=[timestamp]' border='0' width='1' height='1'/>"
    },
    {
        "type": "link",
        "sizes": [
            "300x600"
        ],
        "tcs": [],
        "name": "volaris-mx_adg_ABRIL24_dis_prs-1_HILTON-JULIO",
        "landing": "https://a2.adform.net/C/?bn=74764272",
        "aws_path_1": "VOLARIS/2024/07/hilton/",
        "aws_path_2": ".jpg",
        "url": "https://a2.adform.net/C/?bn=74764272",
        "impression_tag": "<img src='https://a2.adform.net/adfserve/?bn=74764272;1x1inv=1;srctype=3;ord=[timestamp]' border='0' width='1' height='1'/>"
    },
    {
        "type": "link",
        "sizes": [
            "468x60"
        ],
        "tcs": [],
        "name": "volaris-mx_adg_ABRIL24_dis_prs-1_HILTON-JULIO",
        "landing": "https://a2.adform.net/C/?bn=74764269",
        "aws_path_1": "VOLARIS/2024/07/hilton/",
        "aws_path_2": ".jpg",
        "url": "https://a2.adform.net/C/?bn=74764269",
        "impression_tag": "<img src='https://a2.adform.net/adfserve/?bn=74764269;1x1inv=1;srctype=3;ord=[timestamp]' border='0' width='1' height='1'/>"
    },
    {
        "type": "link",
        "sizes": [
            "728x90"
        ],
        "tcs": [],
        "name": "volaris-mx_adg_ABRIL24_dis_prs-1_HILTON-JULIO",
        "landing": "https://a2.adform.net/C/?bn=74764264",
        "aws_path_1": "VOLARIS/2024/07/hilton/",
        "aws_path_2": ".jpg",
        "url": "https://a2.adform.net/C/?bn=74764264",
        "impression_tag": "<img src='https://a2.adform.net/adfserve/?bn=74764264;1x1inv=1;srctype=3;ord=[timestamp]' border='0' width='1' height='1'/>"
    },
    {
        "type": "link",
        "sizes": [
            "160x600"
        ],
        "tcs": [],
        "name": "volaris-mx_adg_ABRIL24_dis_prs-1_HARD-ROCK-JULIO",
        "landing": "https://a2.adform.net/C/?bn=74764263",
        "aws_path_1": "VOLARIS/2024/07/rock/",
        "aws_path_2": ".jpg",
        "url": "https://a2.adform.net/C/?bn=74764263",
        "impression_tag": "<img src='https://a2.adform.net/adfserve/?bn=74764263;1x1inv=1;srctype=3;ord=[timestamp]' border='0' width='1' height='1'/>"
    },
    {
        "type": "link",
        "sizes": [
            "300x250"
        ],
        "tcs": [],
        "name": "volaris-mx_adg_ABRIL24_dis_prs-1_HARD-ROCK-JULIO",
        "landing": "https://a2.adform.net/C/?bn=74764298",
        "aws_path_1": "VOLARIS/2024/07/rock/",
        "aws_path_2": ".jpg",
        "url": "https://a2.adform.net/C/?bn=74764298",
        "impression_tag": "<img src='https://a2.adform.net/adfserve/?bn=74764298;1x1inv=1;srctype=3;ord=[timestamp]' border='0' width='1' height='1'/>"
    },
    {
        "type": "link",
        "sizes": [
            "300x600"
        ],
        "tcs": [],
        "name": "volaris-mx_adg_ABRIL24_dis_prs-1_HARD-ROCK-JULIO",
        "landing": "https://a2.adform.net/C/?bn=74764277",
        "aws_path_1": "VOLARIS/2024/07/rock/",
        "aws_path_2": ".jpg",
        "url": "https://a2.adform.net/C/?bn=74764277",
        "impression_tag": "<img src='https://a2.adform.net/adfserve/?bn=74764298;1x1inv=1;srctype=3;ord=[timestamp]' border='0' width='1' height='1'/>"
    },
    {
        "type": "link",
        "sizes": [
            "468x60"
        ],
        "tcs": [],
        "name": "volaris-mx_adg_ABRIL24_dis_prs-1_HARD-ROCK-JULIO",
        "landing": "https://a2.adform.net/C/?bn=74764286",
        "aws_path_1": "VOLARIS/2024/07/rock/",
        "aws_path_2": ".jpg",
        "url": "https://a2.adform.net/C/?bn=74764286",
        "impression_tag": "<img src='https://a2.adform.net/adfserve/?bn=74764286;1x1inv=1;srctype=3;ord=[timestamp]' border='0' width='1' height='1'/>"
    },
    {
        "type": "link",
        "sizes": [
            "728x90"
        ],
        "tcs": [],
        "name": "volaris-mx_adg_ABRIL24_dis_prs-1_HARD-ROCK-JULIO",
        "landing": "https://a2.adform.net/C/?bn=74764301",
        "aws_path_1": "VOLARIS/2024/07/rock/",
        "aws_path_2": ".jpg",
        "url": "https://a2.adform.net/C/?bn=74764301",
        "impression_tag": "<img src='https://a2.adform.net/adfserve/?bn=74764301;1x1inv=1;srctype=3;ord=[timestamp]' border='0' width='1' height='1'/>"
    }
]